README.rst
setup.py
epysteme/__init__.py
epysteme/data_sets.py
epysteme/db_interfacing.py
epysteme/models.py
epysteme/regression.py
epysteme.egg-info/PKG-INFO
epysteme.egg-info/SOURCES.txt
epysteme.egg-info/dependency_links.txt
epysteme.egg-info/requires.txt
epysteme.egg-info/top_level.txt