Metadata-Version: 1.1
Name: epysteme
Version: 0.1.0
Summary: A neat machine learning package for python
Home-page: https://github.com/sjpet/epysteme
Author: Stefan Peterson
Author-email: stefan.peterson@rubico.com
License: mit
Download-URL: https://github.com/sjpet/epysteme/tarball/0.1.0
Keywords: machine learning data mining out-of-memory
Platform: UNKNOWN
Classifier: Development Status :: 2 - Pre-Alpha
Classifier: Intended Audience :: Science/Research
Classifier: Intended Audience :: Developers
Classifier: License :: OSI Approved :: MIT License
Classifier: Topic :: Scientific/Engineering
Classifier: Programming Language :: Python :: 3
